brujula/__init__.py
brujula/main.py
brujula-0.1.0.dist-info/METADATA
brujula-0.1.0.dist-info/WHEEL
brujula-0.1.0.dist-info/RECORD
